Metadata-Version: 2.4
Name: pytelegrambotapi_fixed
Version: 4.12.8
Summary: fixed version of pyTelegramBotApi
Home-page: https://github.com/molokov-klim/pyTelegramBotAPI_fixed
License: MIT
Platform: any
Classifier: Framework :: Pytest
Classifier: Intended Audience :: Developers
Classifier: License :: OSI Approved :: MIT License
Classifier: Operating System :: OS Independent
Classifier: Programming Language :: Python
Classifier: Programming Language :: Python :: 3
Classifier: Topic :: Software Development :: Quality Assurance
Classifier: Topic :: Software Development :: Testing
Classifier: Topic :: Utilities
Classifier: Topic :: Software Development :: Libraries :: Python Modules
Requires-Python: >=3.9
License-File: LICENSE
Requires-Dist: pytest
Requires-Dist: requests==2.31.0
Requires-Dist: wheel==0.38.1
Requires-Dist: aiohttp==3.9.0
Provides-Extra: test
Requires-Dist: beautifulsoup4; extra == "test"
Requires-Dist: lxml; extra == "test"
Requires-Dist: requests; extra == "test"
Dynamic: classifier
Dynamic: description
Dynamic: description-content-type
Dynamic: home-page
Dynamic: license
Dynamic: license-file
Dynamic: platform
Dynamic: provides-extra
Dynamic: requires-dist
Dynamic: requires-python
Dynamic: summary
